{
  "registry": "utauv",
  "kind": "singers-registry",
  "version": 2,
  "singers": {
    "emerald": {
      "name": "Emerald",
      "cv": "SouЯ",
      "images": [
        "https://emeraldsingers.github.io/images/Emerald2025NoLogo.webp"
      ],
      "description": "Emerald is a Devil male virtual singer with versatile CVVC and CVC RUS voicebanks, featuring normal, childish, dark, and soft tones.",
      "website_url": "https://emeraldsingers.github.io/singer/emerald",
      "characterData": {
        "Species": "Devil",
        "Gender": "Male",
        "Age": "14 years old",
        "Height": "158 cm",
        "Weight": "Unknown",
        "Birthday": "15.09",
        "Stone": "Emerald"
      },
      "voicebanks": {
        "CVVC": {
          "id": "emerald-cvvc",
          "description": "Main Japanese CVVC package.",
          "url": "https://drive.google.com/file/d/17VhCr9xhFNu_kOXeotAAH7NNtVcaisci/view?usp=drive_link",
          "history": {
            "2.0.0": {
              "url": "https://github.com/emeraldsingers/UtauV_Packages/releases/download/emerald-cvvc-v2.0.0/emerald_cvvc.zip",
              "description": "Current stable release."
            },
            "1.5.0": {
              "url": "https://github.com/emeraldsingers/UtauV_Packages/releases/download/emerald-cvvc-v1.5.0/emerald_cvvc.zip",
              "description": "Pre-rework CVVC map."
            },
            "1.0.0": {
              "url": "https://github.com/emeraldsingers/UtauV_Packages/releases/download/emerald-cvvc-v1.0.0/emerald_cvvc.zip",
              "description": "Legacy initial release."
            }
          },
          "supportedLanguages": [
            "ja"
          ],
          "types": [
            "CVVC"
          ],
          "engines": [
            "UTAU"
          ],
          "install_subdir": "Emerald_CVVC",
          "vocalModes": [
            {
              "name": "Normal",
              "description": "Universal neutral tone",
              "sample": "/samples/emerald/emerald_normalcvvc.mp3"
            },
            {
              "name": "Childish",
              "description": "A light and ringing voice",
              "sample": "/samples/emerald/emerald_childishcvvc.mp3"
            },
            {
              "name": "Dark",
              "description": "Deep and rich tone",
              "sample": "/samples/emerald/emerald_darkcvvc.mp3"
            },
            {
              "name": "Soft",
              "description": "Soft and calm tone",
              "sample": "/samples/emerald/emerald_softcvvc.mp3"
            }
          ]
        },
        "CVC RUS": {
          "id": "emerald-cvc-rus",
          "description": "Russian CVC package.",
          "url": "https://drive.google.com/file/d/1aDjOj-FBu7rl-liJgenPe4t9ls7iZ7qG/view?usp=drive_link",
          "history": {
            "3.6.0": {
              "url": "https://github.com/emeraldsingers/UtauV_Packages/releases/download/emerald-cvcrus-v3.6.0/emerald_cvc_rus.zip",
              "description": "Multipitch, Dark, English phonemes."
            }
          },
          "supportedLanguages": [
            "ru"
          ],
          "types": [
            "CVC"
          ],
          "engines": [
            "UTAU"
          ],
          "install_subdir": "Emerald_CVC_RUS"
        }
      }
    }
  }
}
